<?xml version="1.0"?>
<labs>
    <lab id="selva_3928">
        <lab_info>
            <ftp_server>10.32.8.97</ftp_server>
            <tftp_server>10.32.8.97</tftp_server>
            <package>saos-16-07-95-0095</package>
            <package_path>sramasam/build</package_path>
            <base_config_path>config/topology/base</base_config_path>
            <config_path>config/topology</config_path>
        </lab_info>
        <dut>
            <name>A24-11-3928</name>
            <type>eredan</type>
            <management_access>10.33.40.133</management_access>
            <console_access>10.33.50.31 4009</console_access>
            <config_file></config_file>
        </dut>
        <dut>
            <name>A24-12-3928</name>
            <type>eredan</type>
            <management_access>10.33.40.137</management_access>
            <console_access>10.33.50.31 4008</console_access>
            <config_file></config_file>
        </dut>
        <dut>
            <name>A24-13-3928</name>
            <type>eredan</type>
            <management_access>10.33.40.148</management_access>
            <console_access>10.33.50.31 4007</console_access>
            <config_file></config_file>
        </dut>
        <dut>
            <name>A24-14-3928</name>
            <type>eredan</type>
            <management_access>10.33.40.160</management_access>
            <console_access>10.33.50.31 4006</console_access>
            <config_file></config_file>
        </dut>
        <dut>
            <name>A24-16-3928</name>
            <type>eredan</type>
            <management_access>10.33.40.165</management_access>
            <console_access>10.33.50.31 4005</console_access>
            <config_file></config_file>
        </dut>
    </lab>
</labs>
